eventing/__init__.py
eventing/exceptions.py
eventing/validation.py
eventing-0.3.0.dist-info/LICENSE
eventing-0.3.0.dist-info/WHEEL
eventing-0.3.0.dist-info/METADATA
eventing-0.3.0.dist-info/RECORD
