Metadata-Version: 2.1
Name: eventing
Version: 0.3.0
Summary: A pythonic event emitter inspired by Node.js' EventEmitter and Python's logging libraries.
Keywords: events,eventemitter,logging,node
Author-email: Tim Johansson <tim.den.vilde@gmail.com>
Requires-Python: >=3.9,<4
Classifier: Development Status :: 3 - Alpha
Classifier: Intended Audience :: Developers
Classifier: License :: OSI Approved :: MIT License
Classifier: Operating System :: OS Independent
Classifier: Programming Language :: Python :: 3
Classifier: Programming Language :: Python :: 3 :: Only
Classifier: Programming Language :: Python :: 3.9
Classifier: Programming Language :: Python :: 3.10
Classifier: Programming Language :: Python :: Implementation :: CPython
Requires-Dist: flit ==3.7.1 ; extra == "dev"
Requires-Dist: tox ==3.25.0 ; extra == "dev"
Requires-Dist: sphinx ==4.5.0 ; extra == "doc"
Requires-Dist: sphinx_rtd_theme ==1.0.0 ; extra == "doc"
Requires-Dist: pre-commit ==2.19.0 ; extra == "pre-commit"
Requires-Dist: pytest ==7.1.2 ; extra == "test"
Requires-Dist: pytest-asyncio ==0.18.3 ; extra == "test"
Requires-Dist: pytest-cov ==3.0.0 ; extra == "test"
Project-URL: Changelog, https://github.com/tim-timman/eventing/blob/master/CHANGELOG.md
Project-URL: Documentation, https://eventing.readthedocs.io/en/latest/
Project-URL: Repository, https://github.com/tim-timman/eventing
Provides-Extra: dev
Provides-Extra: doc
Provides-Extra: pre-commit
Provides-Extra: test
